{
  "experiment_id": "exp_33_2",
  "hypothesis": "Different architectures have distinct interference exponents: \u03b3_parametric < \u03b3_slot < \u03b3_delta with spread > 0.3.",
  "outcome": "INCONCLUSIVE",
  "metrics": {
    "acc_slot_n2": 0.0063,
    "acc_slot_n4": 0.0031,
    "acc_slot_n8": 0.0102,
    "acc_slot_n16": 0.0156,
    "acc_slot_n32": 0.0055,
    "acc_slot_n64": 0.0063,
    "acc_delta_n2": 0.3727,
    "acc_delta_n4": 0.093,
    "acc_delta_n8": 0.0148,
    "acc_delta_n16": 0.0141,
    "acc_delta_n32": 0.0039,
    "acc_delta_n64": 0.0039,
    "acc_param_n2": 0.0102,
    "acc_param_n4": 0.0086,
    "acc_param_n8": 0.0039,
    "acc_param_n16": 0.0094,
    "acc_param_n32": 0.007,
    "acc_param_n64": 0.0063,
    "gamma_slot": -0.0884,
    "gamma_delta": 1.3336,
    "gamma_param": 0.0885,
    "gamma_spread": 1.422,
    "r2_slot": 0.043,
    "r2_delta": 0.911,
    "r2_param": 0.1066,
    "ordering_ok": 0
  },
  "notes": "\u03b3 ordering: param=0.089 < slot=-0.088 < delta=1.334, spread=1.422, R\u00b2: slot=0.043 delta=0.911 param=0.107. Ordering correct: False.",
  "error": "",
  "timestamp": "2026-03-09T15:03:58.451996+00:00",
  "duration_seconds": 971.8562221659813,
  "config": {
    "hidden_dim": 64,
    "vocab_size": 256,
    "steps": 400,
    "batch": 32,
    "n_pairs_list": [
      2,
      4,
      8,
      16,
      32,
      64
    ],
    "inner_dim": 16,
    "param_bytes_slot": 215552,
    "param_bytes_delta": 215552,
    "param_bytes_param": 207424,
    "activation_bytes": 196608
  },
  "seed": 42
}