{
  "experiment_id": "exp_45_6",
  "hypothesis": "The corrected full system (EMA + split + relative-norm gate) maintains write rate in [0.15, 0.85] and accuracy \u2265 EMA-only baseline across all six scale configurations: HIDDEN_DIM \u2208 {32, 64, 128} \u00d7 SEQ_LEN \u2208 {32, 96}.",
  "outcome": "REFUTED",
  "metrics": {
    "acc_baseline_h32_s32": 0.0609,
    "acc_full_h32_s32": 0.062,
    "wr_full_h32_s32": 0.9483,
    "wr_ok_h32_s32": false,
    "acc_ok_h32_s32": true,
    "acc_baseline_h32_s96": 0.0391,
    "acc_full_h32_s96": 0.0396,
    "wr_full_h32_s96": 0.3084,
    "wr_ok_h32_s96": true,
    "acc_ok_h32_s96": true,
    "acc_baseline_h64_s32": 0.1823,
    "acc_full_h64_s32": 0.1781,
    "wr_full_h64_s32": 0.9677,
    "wr_ok_h64_s32": false,
    "acc_ok_h64_s32": false,
    "acc_baseline_h64_s96": 0.1911,
    "acc_full_h64_s96": 0.1922,
    "wr_full_h64_s96": 0.3156,
    "wr_ok_h64_s96": true,
    "acc_ok_h64_s96": true,
    "acc_baseline_h128_s32": 0.2328,
    "acc_full_h128_s32": 0.2448,
    "wr_full_h128_s32": 0.9677,
    "wr_ok_h128_s32": false,
    "acc_ok_h128_s32": true,
    "acc_baseline_h128_s96": 0.2354,
    "acc_full_h128_s96": 0.2276,
    "wr_full_h128_s96": 0.3158,
    "wr_ok_h128_s96": true,
    "acc_ok_h128_s96": false,
    "all_write_rates_in_range": false,
    "all_accs_at_least_baseline": false
  },
  "notes": "all_wr_ok=False, all_acc_ok=False. Gate write rate collapsed or accuracy degraded at one or more scale configs.",
  "error": "",
  "timestamp": "2026-03-10T19:02:43.043793+00:00",
  "duration_seconds": 1024.187291354,
  "config": {},
  "seed": 42
}